secondtoclock/__init__.py
secondtoclock/secondtoclock.py
secondtoclock-0.0.7.dist-info/LICENSE
secondtoclock-0.0.7.dist-info/METADATA
secondtoclock-0.0.7.dist-info/WHEEL
secondtoclock-0.0.7.dist-info/top_level.txt
secondtoclock-0.0.7.dist-info/RECORD
