Metadata-Version: 2.1
Name: secondtoclock
Version: 0.0.7
Summary: A package to convert seconds to clock
Home-page: UNKNOWN
Author: LulubelleIII
Author-email: <uytudef@gmail.com>
License: UNKNOWN
Keywords: python,time,clock,seconds to clock,time converter
Platform: UNKNOWN
Classifier: Development Status :: 1 - Planning
Classifier: Intended Audience :: Developers
Classifier: Programming Language :: Python :: 3
Classifier: Operating System :: Unix
Classifier: Operating System :: MacOS :: MacOS X
Classifier: Operating System :: Microsoft :: Windows
License-File: LICENSE
